Workbook

Sheet Lisez-moi
B2: Planning des épreuves BetPulse
B3: Saison 2026-2027 et suivantes. Données vérifiées sur le web le 16/10/2026.
B5: À quoi sert ce fichier
C6: Il recense toutes les épreuves proposées aux pronostics dans BetPulse : une ligne par épreuve, toutes compétitions confondues.
C7: L'application (ou un script Python) lit l'onglet Épreuves pour savoir quelles épreuves ouvrir aux pronostics et à quelles dates.
B9: Les onglets
C10: Épreuves : la table de données. C'est le seul onglet à mettre à jour au quotidien.
C11: Référentiels : la liste des sports, compétitions, statuts et genres autorisés, avec le nombre d'épreuves et la prochaine date par compétition.
C12: Lisez-moi : cette notice.
B14: Granularité retenue
C15: Sports mécaniques (F1, MotoGP, WRC) : une ligne par week-end de course ou par rallye.
C16: Sports collectifs (football, rugby, handball, hockey, volley, NFL) : une ligne par journée. NBA : une ligne par semaine, plus les temps forts (NBA Cup, All-Star, play-offs, Finales).
C17: Ski alpin et biathlon : une ligne par épreuve (une course = une ligne, hommes et femmes séparés).
C18: Golf, tennis, cyclisme : une ligne par tournoi ou par course (les courses par étapes tiennent sur une ligne, du premier au dernier jour).
B20: Règles de saisie
C21: 1. Une ligne = une épreuve. Ne pas fusionner de cellules, ne pas laisser de ligne vide au milieu de la table.
C22: 2. Les colonnes sport, competition, statut, genre et ouvert_pronos ont une liste déroulante : choisir une valeur de la liste.
C23: 3. Les dates se saisissent au format JJ/MM/AAAA. Les heures sont en heure de Paris (HH:MM).
C24: 4. L'identifiant (colonne id) ne se modifie jamais. Pour une nouvelle épreuve : CODE-SAISON-NUMÉRO, le code étant celui de l'onglet Référentiels (ex. F1-2027-025).
C25: 5. Une épreuve annulée ou reportée n'est pas supprimée : changer son statut et préciser la raison dans notes.
C26: 6. À chaque vérification, mettre à jour source_url et date_verification.
C27: 7. La colonne avancement se calcule seule. Pour une nouvelle ligne, recopier la formule de la ligne du dessus (dans Google Sheets, elle s'étend toute seule).
B29: Code couleur
C30: Ligne grisée : épreuve terminée.
C31: Statut en orange : date provisoire. Statut en rouge : date à confirmer, reportée ou annulée.
B33: Lecture en Python
C34: Voir planning/lire_planning.py dans le dépôt BetPulse. Le script lit l'onglet Épreuves (export CSV ou API Google Sheets) et renvoie un DataFrame pandas.
B36: Dictionnaire des colonnes (onglet Épreuves)
B37: Colonne | C37: Contenu
B38: id | C38: Identifiant unique et stable : CODE-SAISON-NUMÉRO. Ne jamais le modifier une fois créé (le code Python s'en sert comme clé).
B39: sport | C39: Sport, choisi dans la liste (onglet Référentiels).
B40: competition | C40: Compétition, choisie dans la liste (onglet Référentiels).
B41: saison | C41: Saison : 2026-2027 pour les sports d'hiver et les championnats à cheval sur deux années, 2026 ou 2027 pour les calendriers sur une année civile.
B42: phase | C42: Phase de la compétition : saison régulière, phase de ligue, play-offs, finale, discipline (ski, biathlon)...
B43: manche | C43: Numéro de journée, de semaine ou de manche. Vide si la phase n'est pas numérotée.
B44: intitule | C44: Libellé lisible de l'épreuve, tel qu'il sera affiché dans BetPulse.
B45: date_debut | C45: Premier jour de l'épreuve (format JJ/MM/AAAA).
B46: date_fin | C46: Dernier jour de l'épreuve. Identique à date_debut pour une épreuve d'un jour.
B47: heure_debut | C47: Heure de départ, heure de Paris (HH:MM). Renseignée seulement si elle est officielle.
B48: fuseau | C48: Fuseau horaire de heure_debut. Toujours Europe/Paris.
... B57: avancement | C57: Calculé automatiquement (ne pas saisir) : À venir, En cours ou Terminé selon la date du jour.

Sheet Épreuves
A1: id | B1: sport | C1: competition | D1: saison | E1: phase | F1: manche | G1: intitule | H1: date_debut | I1: date_fin | J1: heure_debut | K1: fuseau | L1: lieu | M1: pays | N1: genre | O1: statut | P1: ouvert_pronos | Q1: source_url | R1: date_verification | S1: notes | T1: avancement
A2: L1-2627-001 | B2: Football | C2: Ligue 1 | D2: 2026-2027 | E2: Saison régulière | F2: 1 | G2: Ligue 1 – Journée 1 | H2: 46255 | I2: 46257 | K2: Europe/Paris | M2: France | N2: Hommes | O2: Officiel | P2: Oui | Q2: https://ligue1.com/fr/articles/l1_article_5284-ligue-1-mc-donald-s-le-calendrier-de-la-saison-26-27 | R2: 46311 | S2: Ouverture de la saison (21-23 août) | T2: =IF(H2="","",IF(MAX(H2,I2)<TODAY(),"Terminé",IF(H2<=TODAY(),"En cours","À venir")))
A3: L1-2627-002 | B3: Football | C3: Ligue 1 | D3: 2026-2027 | E3: Saison régulière | F3: 2 | G3: Ligue 1 – Journée 2 | H3: 46262 | I3: 46264 | K3: Europe/Paris | M3: France | N3: Hommes | O3: Officiel | P3: Oui | Q3: https://ligue1.com/fr/articles/l1_article_5435-programmation-tv-des-2-premieres-journees-de-ligue-1-mc-donald-s-2627 | R3: 46311 | S3: Week-end du 29 août ; jours exacts par match non vérifiés | T3: =IF(H3="","",IF(MAX(H3,I3)<TODAY(),"Terminé",IF(H3<=TODAY(),"En cours","À venir")))
A4: L1-2627-003 | B4: Football | C4: Ligue 1 | D4: 2026-2027 | E4: Saison régulière | F4: 3 | G4: Ligue 1 – Journée 3 | H4: 46268 | I4: 46271 | K4: Europe/Paris | M4: France | N4: Hommes | O4: Officiel | P4: Oui | Q4: https://ligue1.com/fr/articles/l1_article_5572-programmation-tv-j3-ligue-1-mc-donald-s-2627 | R4: 46311 | S4: Ouverture le jeudi 3 septembre (Toulouse–LOSC) | T4: =IF(H4="","",IF(MAX(H4,I4)<TODAY(),"Terminé",IF(H4<=TODAY(),"En cours","À venir")))
A5: L1-2627-004 | B5: Football | C5: Ligue 1 | D5: 2026-2027 | E5: Saison régulière | F5: 4 | G5: Ligue 1 – Journée 4 | H5: 46276 | I5: 46278 | K5: Europe/Paris | M5: France | N5: Hommes | O5: Officiel | P5: Oui | Q5: https://ligue1.com/fr/articles/l1_article_5562-programmation-tv-j4-2 | R5: 46311 | T5: =IF(H5="","",IF(MAX(H5,I5)<TODAY(),"Terminé",IF(H5<=TODAY(),"En cours","À venir")))
A6: L1-2627-005 | B6: Football | C6: Ligue 1 | D6: 2026-2027 | E6: Saison régulière | F6: 5 | G6: Ligue 1 – Journée 5 | H6: 46283 | I6: 46285 | K6: Europe/Paris | M6: France | N6: Hommes | O6: Officiel | P6: Oui | Q6: https://ligue1.com/fr/articles/l1_article_5790-programmation-tv-j5-ligue-1-2026-2027 | R6: 46311 | S6: Trêve internationale ensuite (21 sept.–6 oct.) | T6: =IF(H6="","",IF(MAX(H6,I6)<TODAY(),"Terminé",IF(H6<=TODAY(),"En cours","À venir")))
A7: L1-2627-006 | B7: Football | C7: Ligue 1 | D7: 2026-2027 | E7: Saison régulière | F7: 6 | G7: Ligue 1 – Journée 6 | H7: 46304 | I7: 46306 | K7: Europe/Paris | M7: France | N7: Hommes | O7: Officiel | P7: Oui | Q7: https://ligue1.com/fr/articles/l1_article_5797-programmations-tv-j6-j7-et-j8-l1-2627 | R7: 46311 | T7: =IF(H7="","",IF(MAX(H7,I7)<TODAY(),"Terminé",IF(H7<=TODAY(),"En cours","À venir")))
A8: L1-2627-007 | B8: Football | C8: Ligue 1 | D8: 2026-2027 | E8: Saison régulière | F8: 7 | G8: Ligue 1 – Journée 7 | H8: 46311 | I8: 46313 | K8: Europe/Paris | M8: France | N8: Hommes | O8: Officiel | P8: Oui | Q8: https://ligue1.com/fr/articles/l1_article_5797-programmations-tv-j6-j7-et-j8-l1-2627 | R8: 46311 | T8: =IF(H8="","",IF(MAX(H8,I8)<TODAY(),"Terminé",IF(H8<=TODAY(),"En cours","À venir")))
A9: L1-2627-008 | B9: Football | C9: Ligue 1 | D9: 2026-2027 | E9: Saison régulière | F9: 8 | G9: Ligue 1 – Journée 8 | H9: 46318 | I9: 46320 | K9: Europe/Paris | M9: France | N9: Hommes | O9: Officiel | P9: Oui | Q9: https://ligue1.com/fr/articles/l1_article_5797-programmations-tv-j6-j7-et-j8-l1-2627 | R9: 46311 | T9: =IF(H9="","",IF(MAX(H9,I9)<TODAY(),"Terminé",IF(H9<=TODAY(),"En cours","À venir")))
A10: L1-2627-009 | B10: Football | C10: Ligue 1 | D10: 2026-2027 | E10: Saison régulière | F10: 9 | G10: Ligue 1 – Journée 9 | H10: 46325 | I10: 46327 | K10: Europe/Paris | M10: France | N10: Hommes | O10: Officiel | P10: Oui | Q10: https://ligue1.com/fr/articles/l1_article_5805-programmation-tv-j9-1 | R10: 46311 | T10: =IF(H10="","",IF(MAX(H10,I10)<TODAY(),"Terminé",IF(H10<=TODAY(),"En cours","À venir")))
A11: L1-2627-010 | B11: Football | C11: Ligue 1 | D11: 2026-2027 | E11: Saison régulière | F11: 10 | G11: Ligue 1 – Journée 10 | H11: 46332 | I11: 46334 | K11: Europe/Paris | M11: France | N11: Hommes | O11: Officiel | P11: Oui | Q11: https://ligue1.com/fr/articles/l1_article_5839-programmation-tv-j10-j11-ligue-1-2026-2027 | R11: 46311 | T11: =IF(H11="","",IF(MAX(H11,I11)<TODAY(),"Terminé",IF(H11<=TODAY(),"En cours","À venir")))
A12: L1-2627-011 | B12: Football | C12: Ligue 1 | D12: 2026-2027 | E12: Saison régulière | F12: 11 | G12: Ligue 1 – Journée 11 | H12: 46346 | I12: 46348 | K12: Europe/Paris | M12: France | N12: Hommes | O12: Provisoire | P12: Oui | Q12: https://ligue1.com/fr/articles/l1_article_5839-programmation-tv-j10-j11-ligue-1-2026-2027 | R12: 46311 | S12: Programmation TV publiée (J10-J11) ; jours exacts non vérifiés | T12: =IF(H12="","",IF(MAX(H12,I12)<TODAY(),"Terminé",IF(H12<=TODAY(),"En cours","À venir")))
A13: L1-2627-012 | B13: Football | C13: Ligue 1 | D13: 2026-2027 | E13: Saison régulière | F13: 12 | G13: Ligue 1 – Journée 12 | H13: 46353 | I13: 46355 | K13: Europe/Paris | M13: France | N13: Hommes | O13: Provisoire | P13: Oui | Q13: https://www.lfp.fr/assets/L1_MD_2627_CALENDRIER_SOMBRE_920e8f5afd.pdf | R13: 46311 | S13: Programmation TV non publiée | T13: =IF(H13="","",IF(MAX(H13,I13)<TODAY(),"Terminé",IF(H13<=TODAY(),"En cours","À venir")))
A14: L1-2627-013 | B14: Football | C14: Ligue 1 | D14: 2026-2027 | E14: Saison régulière | F14: 13 | G14: Ligue 1 – Journée 13 | H14: 46360 | I14: 46362 | K14: Europe/Paris | M14: France | N14: Hommes | O14: Provisoire | P14: Oui | Q14: https://www.lfp.fr/assets/L1_MD_2627_CALENDRIER_SOMBRE_920e8f5afd.pdf | R14: 46311 | S14: Programmation TV non publiée | T14: =IF(H14="","",IF(MAX(H14,I14)<TODAY(),"Terminé",IF(H14<=TODAY(),"En cours","À venir")))
A15: L1-2627-014 | B15: Football | C15: Ligue 1 | D15: 2026-2027 | E15: Saison régulière | F15: 14 | G15: Ligue 1 – Journée 14 | H15: 46367 | I15: 46369 | K15: Europe/Paris | M15: France | N15: Hommes | O15: Provisoire | P15: Oui | Q15: https://www.lfp.fr/assets/L1_MD_2627_CALENDRIER_SOMBRE_920e8f5afd.pdf | R15: 46311 | S15: Dernière journée de 2026 (trêve hivernale) ; programmation TV non publiée | T15: =IF(H15="","",IF(MAX(H15,I15)<TODAY(),"Terminé",IF(H15<=TODAY(),"En cours","À venir")))
A16: L1-2627-015 | B16: Football | C16: Ligue 1 | D16: 2026-2027 | E16: Saison régulière | F16: 15 | G16: Ligue 1 – Journée 15 | H16: 46389 | I16: 46390 | K16: Europe/Paris | M16: France | N16: Hommes | O16: Provisoire | P16: Oui | Q16: https://www.lfp.fr/assets/L1_MD_2627_CALENDRIER_SOMBRE_920e8f5afd.pdf | R16: 46311 | S16: Reprise après la trêve ; week-end du 2 janvier (LFP) ; programmation TV non publiée | T16: =IF(H16="","",IF(MAX(H16,I16)<TODAY(),"Terminé",IF(H16<=TODAY(),"En cours","À venir")))
A17: L1-2627-016 | B17: Football | C17: Ligue 1 | D17: 2026-2027 | E17: Saison régulière | F17: 16 | G17: Ligue 1 – Journée 16 | H17: 46402 | I17: 46404 | K17: Europe/Paris | M17: France | N17: Hommes | O17: Provisoire | P17: Oui | Q17: https://www.lfp.fr/assets/L1_MD_2627_CALENDRIER_SOMBRE_920e8f5afd.pdf | R17: 46311 | S17: Programmation TV non publiée | T17: =IF(H17="","",IF(MAX(H17,I17)<TODAY(),"Terminé",IF(H17<=TODAY(),"En cours","À venir")))
A18: L1-2627-017 | B18: Football | C18: Ligue 1 | D18: 2026-2027 | E18: Saison régulière | F18: 17 | G18: Ligue 1 – Journée 17 | H18: 46409 | I18: 46411 | K18: Europe/Paris | M18: France | N18: Hommes | O18: Provisoire | P18: Oui | Q18: https://www.lfp.fr/assets/L1_MD_2627_CALENDRIER_SOMBRE_920e8f5afd.pdf | R18: 46311 | S18: Programmation TV non publiée | T18: =IF(H18="","",IF(MAX(H18,I18)<TODAY(),"Terminé",IF(H18<=TODAY(),"En cours","À venir")))
A19: L1-2627-018 | B19: Football | C19: Ligue 1 | D19: 2026-2027 | E19: Saison régulière | F19: 18 | G19: Ligue 1 – Journée 18 | H19: 46416 | I19: 46418 | K19: Europe/Paris | M19: France | N19: Hommes | O19: Provisoire | P19: Oui | Q19: https://www.lfp.fr/assets/L1_MD_2627_CALENDRIER_SOMBRE_920e8f5afd.pdf | R19: 46311 | S19: Programmation TV non publiée | T19: =IF(H19="","",IF(MAX(H19,I19)<TODAY(),"Terminé",IF(H19<=TODAY(),"En cours","À venir")))
A20: L1-2627-019 | B20: Football | C20: Ligue 1 | D20: 2026-2027 | E20: Saison régulière | F20: 19 | G20: Ligue 1 – Journée 19 | H20: 46423 | I20: 46425 | K20: Europe/Paris | M20: France | N20: Hommes | O20: Provisoire | P20: Oui | Q20: https://www.lfp.fr/assets/L1_MD_2627_CALENDRIER_SOMBRE_920e8f5afd.pdf | R20: 46311 | S20: Programmation TV non publiée | T20: =IF(H20="","",IF(MAX(H20,I20)<TODAY(),"Terminé",IF(H20<=TODAY(),"En cours","À venir")))
A21: L1-2627-020 | B21: Football | C21: Ligue 1 | D21: 2026-2027 | E21: Saison régulière | F21: 20 | G21: Ligue 1 – Journée 20 | H21: 46430 | I21: 46432 | K21: Europe/Paris | M21: France | N21: Hommes | O21: Provisoire | P21: Oui | Q21: https://www.lfp.fr/assets/L1_MD_2627_CALENDRIER_SOMBRE_920e8f5afd.pdf | R21: 46311 | S21: Programmation TV non publiée | T21: =IF(H21="","",IF(MAX(H21,I21)<TODAY(),"Terminé",IF(H21<=TODAY(),"En cours","À venir")))
A22: L1-2627-021 | B22: Football | C22: Ligue 1 | D22: 2026-2027 | E22: Saison régulière | F22: 21 | G22: Ligue 1 – Journée 21 | H22: 46437 | I22: 46439 | K22: Europe/Paris | M22: France | N22: Hommes | O22: Provisoire | P22: Oui | Q22: https://www.lfp.fr/assets/L1_MD_2627_CALENDRIER_SOMBRE_920e8f5afd.pdf | R22: 46311 | S22: Programmation TV non publiée | T22: =IF(H22="","",IF(MAX(H22,I22)<TODAY(),"Terminé",IF(H22<=TODAY(),"En cours","À venir")))
A23: L1-2627-022 | B23: Football | C23: Ligue 1 | D23: 2026-2027 | E23: Saison régulière | F23: 22 | G23: Ligue 1 – Journée 22 | H23: 46444 | I23: 46446 | K23: Europe/Paris | M23: France | N23: Hommes | O23: Provisoire | P23: Oui | Q23: https://www.lfp.fr/assets/L1_MD_2627_CALENDRIER_SOMBRE_920e8f5afd.pdf | R23: 46311 | S23: Programmation TV non publiée | T23: =IF(H23="","",IF(MAX(H23,I23)<TODAY(),"Terminé",IF(H23<=TODAY(),"En cours","À venir")))
... A35: L1-2627-034 | B35: Football | C35: Ligue 1 | D35: 2026-2027 | E35: Saison régulière | F35: 34 | G35: Ligue 1 – Journée 34 | H35: 46536 | I35: 46536 | K35: Europe/Paris | M35: France | N35: Hommes | O35: Officiel | P35: Oui | Q35: https://ligue1.com/fr/articles/l1_article_5284-ligue-1-mc-donald-s-le-calendrier-de-la-saison-26-27 | R35: 46311 | S35: Dernière journée, multiplex le samedi ; horaire non vérifié | T35: =IF(H35="","",IF(MAX(H35,I35)<TODAY(),"Terminé",IF(H35<=TODAY(),"En cours","À venir")))
A36: L1-2627-035 | B36: Football | C36: Ligue 1 | D36: 2026-2027 | E36: Barrages | G36: Ligue 1 – Barrage d'accession L1/L2 | H36: 46541 | I36: 46544 | K36: Europe/Paris | M36: France | N36: Hommes | O36: Officiel | P36: Oui | Q36: https://www.lfp.fr/article/publication-du-calendrier-general-de-la-ligue-2-bkt-pour-la-saison-2026-2027 | R36: 46311 | S36: 16e de L1 vs vainqueur des play-offs L2 ; aller jeudi 3 juin, retour dimanche 6 juin | T36: =IF(H36="","",IF(MAX(H36,I36)<TODAY(),"Terminé",IF(H36<=TODAY(),"En cours","À venir")))
A37: L2-2627-001 | B37: Football | C37: Ligue 2 | D37: 2026-2027 | E37: Saison régulière | F37: 1 | G37: Ligue 2 – Journée 1 | H37: 46242 | I37: 46242 | K37: Europe/Paris | M37: France | N37: Hommes | O37: Officiel | P37: Oui | Q37: https://ligue1.com/fr/articles/l1_article_5291-programmation-tv-des-2-premieres-journees-de-ligue-2-bkt | R37: 46311 | S37: Journée jouée le samedi (multiplex + affiche à 20h45) | T37: =IF(H37="","",IF(MAX(H37,I37)<TODAY(),"Terminé",IF(H37<=TODAY(),"En cours","À venir")))
A38: L2-2627-002 | B38: Football | C38: Ligue 2 | D38: 2026-2027 | E38: Saison régulière | F38: 2 | G38: Ligue 2 – Journée 2 | H38: 46248 | I38: 46248 | K38: Europe/Paris | M38: France | N38: Hommes | O38: Officiel | P38: Oui | Q38: https://ligue1.com/fr/articles/l1_article_5291-programmation-tv-des-2-premieres-journees-de-ligue-2-bkt | R38: 46311 | S38: Multiplex avancé du samedi 15 au vendredi 14 août | T38: =IF(H38="","",IF(MAX(H38,I38)<TODAY(),"Terminé",IF(H38<=TODAY(),"En cours","À venir")))
A39: L2-2627-003 | B39: Football | C39: Ligue 2 | D39: 2026-2027 | E39: Saison régulière | F39: 3 | G39: Ligue 2 – Journée 3 | H39: 46255 | I39: 46258 | K39: Europe/Paris | M39: France | N39: Hommes | O39: Officiel | P39: Oui | Q39: https://www.lfp.fr/article/ligue-2-bkt-le-calendrier-de-la-saison-2026-2027 | R39: 46311 | S39: Week-end LFP (ven.–lun.) ; jours exacts par match non vérifiés | T39: =IF(H39="","",IF(MAX(H39,I39)<TODAY(),"Terminé",IF(H39<=TODAY(),"En cours","À venir")))
A40: L2-2627-004 | B40: Football | C40: Ligue 2 | D40: 2026-2027 | E40: Saison régulière | F40: 4 | G40: Ligue 2 – Journée 4 | H40: 46262 | I40: 46265 | K40: Europe/Paris | M40: France | N40: Hommes | O40: Officiel | P40: Oui | Q40: https://www.lfp.fr/article/ligue-2-bkt-le-calendrier-de-la-saison-2026-2027 | R40: 46311 | S40: Week-end LFP (ven.–lun.) ; jours exacts par match non vérifiés | T40: =IF(H40="","",IF(MAX(H40,I40)<TODAY(),"Terminé",IF(H40<=TODAY(),"En cours","À venir")))
A41: L2-2627-005 | B41: Football | C41: Ligue 2 | D41: 2026-2027 | E41: Saison régulière | F41: 5 | G41: Ligue 2 – Journée 5 | H41: 46269 | I41: 46272 | K41: Europe/Paris | M41: France | N41: Hommes | O41: Officiel | P41: Oui | Q41: https://www.lfp.fr/article/ligue-2-bkt-le-calendrier-de-la-saison-2026-2027 | R41: 46311 | S41: Week-end LFP (ven.–lun.) ; jours exacts par match non vérifiés | T41: =IF(H41="","",IF(MAX(H41,I41)<TODAY(),"Terminé",IF(H41<=TODAY(),"En cours","À venir")))
A42: L2-2627-006 | B42: Football | C42: Ligue 2 | D42: 2026-2027 | E42: Saison régulière | F42: 6 | G42: Ligue 2 – Journée 6 | H42: 46276 | I42: 46279 | K42: Europe/Paris | M42: France | N42: Hommes | O42: Officiel | P42: Oui | Q42: https://www.lfp.fr/article/ligue-2-bkt-le-calendrier-de-la-saison-2026-2027 | R42: 46311 | S42: Week-end LFP (ven.–lun.) ; jours exacts par match non vérifiés | T42: =IF(H42="","",IF(MAX(H42,I42)<TODAY(),"Terminé",IF(H42<=TODAY(),"En cours","À venir")))
A43: L2-2627-007 | B43: Football | C43: Ligue 2 | D43: 2026-2027 | E43: Saison régulière | F43: 7 | G43: Ligue 2 – Journée 7 | H43: 46283 | I43: 46286 | K43: Europe/Paris | M43: France | N43: Hommes | O43: Officiel | P43: Oui | Q43: https://www.lfp.fr/article/ligue-2-bkt-le-calendrier-de-la-saison-2026-2027 | R43: 46311 | S43: Week-end LFP (ven.–lun.) ; jours exacts par match non vérifiés | T43: =IF(H43="","",IF(MAX(H43,I43)<TODAY(),"Terminé",IF(H43<=TODAY(),"En cours","À venir")))
A44: L2-2627-008 | B44: Football | C44: Ligue 2 | D44: 2026-2027 | E44: Saison régulière | F44: 8 | G44: Ligue 2 – Journée 8 | H44: 46304 | I44: 46307 | K44: Europe/Paris | M44: France | N44: Hommes | O44: Officiel | P44: Oui | Q44: https://ligue1.com/fr/articles/l1_article_5652-programmation-tv-j8-l2-2627 | R44: 46311 | S44: Vendredi multiplex, samedi, lundi (programmation TV) | T44: =IF(H44="","",IF(MAX(H44,I44)<TODAY(),"Terminé",IF(H44<=TODAY(),"En cours","À venir")))
A45: L2-2627-009 | B45: Football | C45: Ligue 2 | D45: 2026-2027 | E45: Saison régulière | F45: 9 | G45: Ligue 2 – Journée 9 | H45: 46311 | I45: 46314 | K45: Europe/Paris | M45: France | N45: Hommes | O45: Officiel | P45: Oui | Q45: https://ligue1.com/fr/articles/l1_article_5695-programmation-tv-j9-ligue-2-2026-2027 | R45: 46311 | S45: Vendredi multiplex, samedi, lundi (programmation TV) | T45: =IF(H45="","",IF(MAX(H45,I45)<TODAY(),"Terminé",IF(H45<=TODAY(),"En cours","À venir")))
A46: L2-2627-010 | B46: Football | C46: Ligue 2 | D46: 2026-2027 | E46: Saison régulière | F46: 10 | G46: Ligue 2 – Journée 10 | H46: 46318 | I46: 46321 | K46: Europe/Paris | M46: France | N46: Hommes | O46: Officiel | P46: Oui | Q46: https://ligue1.com/fr/articles/l1_article_5749-programmation-tv-j10-1 | R46: 46311 | S46: Multiplex vendredi 23 oct. ; date du dernier match non vérifiée | T46: =IF(H46="","",IF(MAX(H46,I46)<TODAY(),"Terminé",IF(H46<=TODAY(),"En cours","À venir")))
A47: L2-2627-011 | B47: Football | C47: Ligue 2 | D47: 2026-2027 | E47: Saison régulière | F47: 11 | G47: Ligue 2 – Journée 11 | H47: 46325 | I47: 46328 | K47: Europe/Paris | M47: France | N47: Hommes | O47: Officiel | P47: Oui | Q47: https://ligue1.com/fr/articles/l1_article_5803-programmation-tv-j11-l2-2627 | R47: 46311 | S47: Vendredi multiplex, samedi, lundi (programmation TV) | T47: =IF(H47="","",IF(MAX(H47,I47)<TODAY(),"Terminé",IF(H47<=TODAY(),"En cours","À venir")))
A48: L2-2627-012 | B48: Football | C48: Ligue 2 | D48: 2026-2027 | E48: Saison régulière | F48: 12 | G48: Ligue 2 – Journée 12 | H48: 46332 | I48: 46335 | K48: Europe/Paris | M48: France | N48: Hommes | O48: Provisoire | P48: Oui | Q48: https://www.lfp.fr/article/ligue-2-bkt-le-calendrier-de-la-saison-2026-2027 | R48: 46311 | S48: Week-end nominal ven.–lun. ; programmation TV non publiée | T48: =IF(H48="","",IF(MAX(H48,I48)<TODAY(),"Terminé",IF(H48<=TODAY(),"En cours","À venir")))
... A70: L2-2627-034 | B70: Football | C70: Ligue 2 | D70: 2026-2027 | E70: Saison régulière | F70: 34 | G70: Ligue 2 – Journée 34 | H70: 46529 | I70: 46529 | K70: Europe/Paris | M70: France | N70: Hommes | O70: Officiel | P70: Oui | Q70: https://www.lfp.fr/article/publication-du-calendrier-general-de-la-ligue-2-bkt-pour-la-saison-2026-2027 | R70: 46311 | S70: Dernière journée, multiplex le samedi ; horaire non vérifié | T70: =IF(H70="","",IF(MAX(H70,I70)<TODAY(),"Terminé",IF(H70<=TODAY(),"En cours","À venir")))
A71: L2-2627-035 | B71: Football | C71: Ligue 2 | D71: 2026-2027 | E71: Play-offs | G71: Ligue 2 – Play-off 1 (4e vs 5e) | H71: 46532 | I71: 46532 | K71: Europe/Paris | M71: France | N71: Hommes | O71: Officiel | P71: Oui | Q71: https://www.lfp.fr/article/publication-du-calendrier-general-de-la-ligue-2-bkt-pour-la-saison-2026-2027 | R71: 46311 | S71: Mardi 25 mai | T71: =IF(H71="","",IF(MAX(H71,I71)<TODAY(),"Terminé",IF(H71<=TODAY(),"En cours","À venir")))
A72: L2-2627-036 | B72: Football | C72: Ligue 2 | D72: 2026-2027 | E72: Play-offs | G72: Ligue 2 – Play-off 2 (3e vs vainqueur PO1) | H72: 46535 | I72: 46535 | K72: Europe/Paris | M72: France | N72: Hommes | O72: Officiel | P72: Oui | Q72: https://www.lfp.fr/article/publication-du-calendrier-general-de-la-ligue-2-bkt-pour-la-saison-2026-2027 | R72: 46311 | S72: Vendredi 28 mai ; le vainqueur dispute le barrage L1/L2 (3 et 6 juin) | T72: =IF(H72="","",IF(MAX(H72,I72)<TODAY(),"Terminé",IF(H72<=TODAY(),"En cours","À venir")))
A73: L2-2627-037 | B73: Football | C73: Ligue 2 | D73: 2026-2027 | E73: Barrages | G73: Ligue 2 – Barrage de maintien (16e L2 vs 3e division) | H73: 46539 | I73: 46544 | K73: Europe/Paris | M73: France | N73: Hommes | O73: Officiel | P73: Oui | Q73: https://www.lfp.fr/article/publication-du-calendrier-general-de-la-ligue-2-bkt-pour-la-saison-2026-2027 | R73: 46311 | S73: Aller mardi 1er juin, retour dimanche 6 juin ; adversaire = 3e de National selon la source (création Ligue 3 à vérifier) | T73: =IF(H73="","",IF(MAX(H73,I73)<TODAY(),"Terminé",IF(H73<=TODAY(),"En cours","À venir")))
A74: LIGA-2627-001 | B74: Football | C74: LaLiga | D74: 2026-2027 | E74: Saison régulière | F74: 1 | G74: LaLiga – Journée 1 | H74: 46249 | I74: 46261 | K74: Europe/Paris | M74: Espagne | N74: Hommes | O74: Officiel | P74: Oui | Q74: https://www.laliga.com/noticias/horarios-de-la-primera-jornada-de-laliga-ea-sports-2026-27 | R74: 46311 | S74: Jornada étalée : clubs mondialistes jouent les 25-27 août | T74: =IF(H74="","",IF(MAX(H74,I74)<TODAY(),"Terminé",IF(H74<=TODAY(),"En cours","À venir")))
A75: LIGA-2627-002 | B75: Football | C75: LaLiga | D75: 2026-2027 | E75: Saison régulière | F75: 2 | G75: LaLiga – Journée 2 | H75: 46254 | I75: 46258 | K75: Europe/Paris | M75: Espagne | N75: Hommes | O75: Officiel | P75: Oui | Q75: https://www.laliga.com/noticias/horarios-de-la-segunda-jornada-de-laliga-ea-sports-2026-27 | R75: 46311 | S75: Du jeudi 20 au lundi 24 août | T75: =IF(H75="","",IF(MAX(H75,I75)<TODAY(),"Terminé",IF(H75<=TODAY(),"En cours","À venir")))
A76: LIGA-2627-003 | B76: Football | C76: LaLiga | D76: 2026-2027 | E76: Saison régulière | F76: 3 | G76: LaLiga – Journée 3 | H76: 46262 | I76: 46265 | K76: Europe/Paris | M76: Espagne | N76: Hommes | O76: Officiel | P76: Oui | Q76: https://www.laliga.com/noticias/horarios-de-la-tercera-jornada-de-laliga-ea-sports-2026-27 | R76: 46311 | T76: =IF(H76="","",IF(MAX(H76,I76)<TODAY(),"Terminé",IF(H76<=TODAY(),"En cours","À venir")))
A77: LIGA-2627-004 | B77: Football | C77: LaLiga | D77: 2026-2027 | E77: Saison régulière | F77: 4 | G77: LaLiga – Journée 4 | H77: 46269 | I77: 46272 | K77: Europe/Paris | M77: Espagne | N77: Hommes | O77: Officiel | P77: Oui | Q77: https://www.laliga.com/noticias/horarios-de-la-cuarta-jornada-de-laliga-ea-sports-2026-27 | R77: 46311 | T77: =IF(H77="","",IF(MAX(H77,I77)<TODAY(),"Terminé",IF(H77<=TODAY(),"En cours","À venir")))
A78: LIGA-2627-005 | B78: Football | C78: LaLiga | D78: 2026-2027 | E78: Saison régulière | F78: 5 | G78: LaLiga – Journée 5 | H78: 46276 | I78: 46279 | K78: Europe/Paris | M78: Espagne | N78: Hommes | O78: Officiel | P78: Oui | Q78: https://www.laliga.com/noticias/horarios-de-la-quinta-jornada-de-laliga-ea-sports-2026-27 | R78: 46311 | T78: =IF(H78="","",IF(MAX(H78,I78)<TODAY(),"Terminé",IF(H78<=TODAY(),"En cours","À venir")))
A79: LIGA-2627-006 | B79: Football | C79: LaLiga | D79: 2026-2027 | E79: Saison régulière | F79: 6 | G79: LaLiga – Journée 6 | H79: 46280 | I79: 46282 | K79: Europe/Paris | M79: Espagne | N79: Hommes | O79: Officiel | P79: Oui | Q79: https://www.laliga.com/noticias/horarios-de-la-sexta-jornada-de-laliga-ea-sports-2026-27 | R79: 46311 | S79: Journée en semaine (mar.–jeu.) | T79: =IF(H79="","",IF(MAX(H79,I79)<TODAY(),"Terminé",IF(H79<=TODAY(),"En cours","À venir")))
A80: LIGA-2627-007 | B80: Football | C80: LaLiga | D80: 2026-2027 | E80: Saison régulière | F80: 7 | G80: LaLiga – Journée 7 | H80: 46283 | I80: 46285 | K80: Europe/Paris | M80: Espagne | N80: Hommes | O80: Officiel | P80: Oui | Q80: https://www.laliga.com/noticias/horarios-de-la-septima-jornada-de-laliga-ea-sports-2026-27 | R80: 46311 | T80: =IF(H80="","",IF(MAX(H80,I80)<TODAY(),"Terminé",IF(H80<=TODAY(),"En cours","À venir")))
A81: LIGA-2627-008 | B81: Football | C81: LaLiga | D81: 2026-2027 | E81: Saison régulière | F81: 8 | G81: LaLiga – Journée 8 | H81: 46304 | I81: 46307 | K81: Europe/Paris | M81: Espagne | N81: Hommes | O81: Officiel | P81: Oui | Q81: https://www.laliga.com/noticias/horarios-de-la-octava-jornada-de-laliga-ea-sports-2026-27 | R81: 46311 | T81: =IF(H81="","",IF(MAX(H81,I81)<TODAY(),"Terminé",IF(H81<=TODAY(),"En cours","À venir")))
A82: LIGA-2627-009 | B82: Football | C82: LaLiga | D82: 2026-2027 | E82: Saison régulière | F82: 9 | G82: LaLiga – Journée 9 | H82: 46311 | I82: 46314 | K82: Europe/Paris | M82: Espagne | N82: Hommes | O82: Officiel | P82: Oui | Q82: https://www.laliga.com/noticias/horarios-de-la-novena-jornada-de-laliga-ea-sports-2026-27 | R82: 46311 | T82: =IF(H82="","",IF(MAX(H82,I82)<TODAY(),"Terminé",IF(H82<=TODAY(),"En cours","À venir")))
A83: LIGA-2627-010 | B83: Football | C83: LaLiga | D83: 2026-2027 | E83: Saison régulière | F83: 10 | G83: LaLiga – Journée 10 | H83: 46318 | I83: 46321 | K83: Europe/Paris | M83: Espagne | N83: Hommes | O83: Officiel | P83: Oui | Q83: https://www.laliga.com/noticias/horarios-de-la-decima-jornada-de-laliga-ea-sports-2026-27 | R83: 46311 | S83: Clasico Barça–Real Madrid | T83: =IF(H83="","",IF(MAX(H83,I83)<TODAY(),"Terminé",IF(H83<=TODAY(),"En cours","À venir")))
A84: LIGA-2627-011 | B84: Football | C84: LaLiga | D84: 2026-2027 | E84: Saison régulière | F84: 11 | G84: LaLiga – Journée 11 | H84: 46325 | I84: 46328 | K84: Europe/Paris | M84: Espagne | N84: Hommes | O84: Officiel | P84: Oui | Q84: https://www.laliga.com/noticias/horarios-de-la-undecima-jornada-de-laliga-ea-sports-2026-27 | R84: 46311 | T84: =IF(H84="","",IF(MAX(H84,I84)<TODAY(),"Terminé",IF(H84<=TODAY(),"En cours","À venir")))
A85: LIGA-2627-012 | B85: Football | C85: LaLiga | D85: 2026-2027 | E85: Saison régulière | F85: 12 | G85: LaLiga – Journée 12 | H85: 46332 | I85: 46334 | K85: Europe/Paris | M85: Espagne | N85: Hommes | O85: Officiel | P85: Oui | Q85: https://www.laliga.com/noticias/horarios-de-la-duodecima-jornada-de-laliga-ea-sports-2026-27 | R85: 46311 | T85: =IF(H85="","",IF(MAX(H85,I85)<TODAY(),"Terminé",IF(H85<=TODAY(),"En cours","À venir")))
A86: LIGA-2627-013 | B86: Football | C86: LaLiga | D86: 2026-2027 | E86: Saison régulière | F86: 13 | G86: LaLiga – Journée 13 | H86: 46346 | I86: 46349 | K86: Europe/Paris | M86: Espagne | N86: Hommes | O86: Provisoire | P86: Oui | Q86: https://rfef.es/sites/default/files/2026-06/Campeonato_de_Primera_Division_0.pdf | R86: 46311 | S86: Date de référence RFEF : 22/11 ; fenêtre ven.–lun. ; horaires non publiés | T86: =IF(H86="","",IF(MAX(H86,I86)<TODAY(),"Terminé",IF(H86<=TODAY(),"En cours","À venir")))
A87: LIGA-2627-014 | B87: Football | C87: LaLiga | D87: 2026-2027 | E87: Saison régulière | F87: 14 | G87: LaLiga – Journée 14 | H87: 46353 | I87: 46356 | K87: Europe/Paris | M87: Espagne | N87: Hommes | O87: Provisoire | P87: Oui | Q87: https://rfef.es/sites/default/files/2026-06/Campeonato_de_Primera_Division_0.pdf | R87: 46311 | S87: Date de référence RFEF : 29/11 ; fenêtre ven.–lun. ; horaires non publiés | T87: =IF(H87="","",IF(MAX(H87,I87)<TODAY(),"Terminé",IF(H87<=TODAY(),"En cours","À venir")))
A88: LIGA-2627-015 | B88: Football | C88: LaLiga | D88: 2026-2027 | E88: Saison régulière | F88: 15 | G88: LaLiga – Journée 15 | H88: 46360 | I88: 46363 | K88: Europe/Paris | M88: Espagne | N88: Hommes | O88: Provisoire | P88: Oui | Q88: https://rfef.es/sites/default/files/2026-06/Campeonato_de_Primera_Division_0.pdf | R88: 46311 | S88: Date de référence RFEF : 06/12 ; fenêtre ven.–lun. ; horaires non publiés | T88: =IF(H88="","",IF(MAX(H88,I88)<TODAY(),"Terminé",IF(H88<=TODAY(),"En cours","À venir")))
A89: LIGA-2627-016 | B89: Football | C89: LaLiga | D89: 2026-2027 | E89: Saison régulière | F89: 16 | G89: LaLiga – Journée 16 | H89: 46367 | I89: 46370 | K89: Europe/Paris | M89: Espagne | N89: Hommes | O89: Provisoire | P89: Oui | Q89: https://rfef.es/sites/default/files/2026-06/Campeonato_de_Primera_Division_0.pdf | R89: 46311 | S89: Date de référence RFEF : 13/12 ; fenêtre ven.–lun. ; horaires non publiés | T89: =IF(H89="","",IF(MAX(H89,I89)<TODAY(),"Terminé",IF(H89<=TODAY(),"En cours","À venir")))
A90: LIGA-2627-017 | B90: Football | C90: LaLiga | D90: 2026-2027 | E90: Saison régulière | F90: 17 | G90: LaLiga – Journée 17 | H90: 46374 | I90: 46377 | K90: Europe/Paris | M90: Espagne | N90: Hommes | O90: Provisoire | P90: Oui | Q90: https://rfef.es/sites/default/files/2026-06/Campeonato_de_Primera_Division_0.pdf | R90: 46311 | S90: Date de référence RFEF : 20/12 ; fenêtre ven.–lun. ; horaires non publiés | T90: =IF(H90="","",IF(MAX(H90,I90)<TODAY(),"Terminé",IF(H90<=TODAY(),"En cours","À venir")))
A91: LIGA-2627-018 | B91: Football | C91: LaLiga | D91: 2026-2027 | E91: Saison régulière | F91: 18 | G91: LaLiga – Journée 18 | H91: 46389 | I91: 46391 | K91: Europe/Paris | M91: Espagne | N91: Hommes | O91: Provisoire | P91: Oui | Q91: https://rfef.es/sites/default/files/2026-06/Campeonato_de_Primera_Division_0.pdf | R91: 46311 | S91: Date de référence RFEF : 03/01 ; fenêtre sam.–lun. (1er janvier exclu) ; horaires non publiés | T91: =IF(H91="","",IF(MAX(H91,I91)<TODAY(),"Terminé",IF(H91<=TODAY(),"En cours","À venir")))
A92: LIGA-2627-019 | B92: Football | C92: LaLiga | D92: 2026-2027 | E92: Saison régulière | F92: 19 | G92: LaLiga – Journée 19 | H92: 46395 | I92: 46398 | K92: Europe/Paris | M92: Espagne | N92: Hommes | O92: Provisoire | P92: Oui | Q92: https://rfef.es/sites/default/files/2026-06/Campeonato_de_Primera_Division_0.pdf | R92: 46311 | S92: Date de référence RFEF : 10/01 ; fenêtre ven.–lun. ; horaires non publiés | T92: =IF(H92="","",IF(MAX(H92,I92)<TODAY(),"Terminé",IF(H92<=TODAY(),"En cours","À venir")))
A93: LIGA-2627-020 | B93: Football | C93: LaLiga | D93: 2026-2027 | E93: Saison régulière | F93: 20 | G93: LaLiga – Journée 20 | H93: 46402 | I93: 46405 | K93: Europe/Paris | M93: Espagne | N93: Hommes | O93: Provisoire | P93: Oui | Q93: https://rfef.es/sites/default/files/2026-06/Campeonato_de_Primera_Division_0.pdf | R93: 46311 | S93: Date de référence RFEF : 17/01 ; fenêtre ven.–lun. ; horaires non publiés | T93: =IF(H93="","",IF(MAX(H93,I93)<TODAY(),"Terminé",IF(H93<=TODAY(),"En cours","À venir")))
A94: LIGA-2627-021 | B94: Football | C94: LaLiga | D94: 2026-2027 | E94: Saison régulière | F94: 21 | G94: LaLiga – Journée 21 | H94: 46409 | I94: 46412 | K94: Europe/Paris | M94: Espagne | N94: Hommes | O94: Provisoire | P94: Oui | Q94: https://rfef.es/sites/default/files/2026-06/Campeonato_de_Primera_Division_0.pdf | R94: 46311 | S94: Date de référence RFEF : 24/01 ; fenêtre ven.–lun. ; horaires non publiés | T94: =IF(H94="","",IF(MAX(H94,I94)<TODAY(),"Terminé",IF(H94<=TODAY(),"En cours","À venir")))
A95: LIGA-2627-022 | B95: Football | C95: LaLiga | D95: 2026-2027 | E95: Saison régulière | F95: 22 | G95: LaLiga – Journée 22 | H95: 46416 | I95: 46419 | K95: Europe/Paris | M95: Espagne | N95: Hommes | O95: Provisoire | P95: Oui | Q95: https://rfef.es/sites/default/files/2026-06/Campeonato_de_Primera_Division_0.pdf | R95: 46311 | S95: Date de référence RFEF : 31/01 ; fenêtre ven.–lun. ; horaires non publiés | T95: =IF(H95="","",IF(MAX(H95,I95)<TODAY(),"Terminé",IF(H95<=TODAY(),"En cours","À venir")))
A96: LIGA-2627-023 | B96: Football | C96: LaLiga | D96: 2026-2027 | E96: Saison régulière | F96: 23 | G96: LaLiga – Journée 23 | H96: 46423 | I96: 46426 | K96: Europe/Paris | M96: Espagne | N96: Hommes | O96: Provisoire | P96: Oui | Q96: https://rfef.es/sites/default/files/2026-06/Campeonato_de_Primera_Division_0.pdf | R96: 46311 | S96: Date de référence RFEF : 07/02 ; fenêtre ven.–lun. ; horaires non publiés | T96: =IF(H96="","",IF(MAX(H96,I96)<TODAY(),"Terminé",IF(H96<=TODAY(),"En cours","À venir")))
A97: LIGA-2627-024 | B97: Football | C97: LaLiga | D97: 2026-2027 | E97: Saison régulière | F97: 24 | G97: LaLiga – Journée 24 | H97: 46430 | I97: 46433 | K97: Europe/Paris | M97: Espagne | N97: Hommes | O97: Provisoire | P97: Oui | Q97: https://rfef.es/sites/default/files/2026-06/Campeonato_de_Primera_Division_0.pdf | R97: 46311 | S97: Date de référence RFEF : 14/02 ; fenêtre ven.–lun. ; horaires non publiés | T97: =IF(H97="","",IF(MAX(H97,I97)<TODAY(),"Terminé",IF(H97<=TODAY(),"En cours","À venir")))
... A112: EPL-2627-001 | B112: Football | C112: Premier League | D112: 2026-2027 | E112: Saison régulière | F112: 1 | G112: Premier League – Journée 1 | H112: 46255 | I112: 46258 | K112: Europe/Paris | M112: Angleterre | N112: Hommes | O112: Officiel | P112: Oui | Q112: https://www.premierleague.com/en/news/4675508/premier-league-fixture-schedulereleased-for-season-202627 | R112: 46311 | S112: Arsenal–Coventry ven. 21/08, clôture Fulham–Chelsea lun. 24/08 | T112: =IF(H112="","",IF(MAX(H112,I112)<TODAY(),"Terminé",IF(H112<=TODAY(),"En cours","À venir")))
A113: EPL-2627-002 | B113: Football | C113: Premier League | D113: 2026-2027 | E113: Saison régulière | F113: 2 | G113: Premier League – Journée 2 | H113: 46262 | I113: 46265 | K113: Europe/Paris | M113: Angleterre | N113: Hommes | O113: Officiel | P113: Oui | Q113: https://www.premierleague.com/en/news/4675097/all-380-fixtures-for-202627-premier-league-season | R113: 46311 | T113: =IF(H113="","",IF(MAX(H113,I113)<TODAY(),"Terminé",IF(H113<=TODAY(),"En cours","À venir")))
A114: EPL-2627-003 | B114: Football | C114: Premier League | D114: 2026-2027 | E114: Saison régulière | F114: 3 | G114: Premier League – Journée 3 | H114: 46269 | I114: 46271 | K114: Europe/Paris | M114: Angleterre | N114: Hommes | O114: Officiel | P114: Oui | Q114: https://www.premierleague.com/en/news/4675097/all-380-fixtures-for-202627-premier-league-season | R114: 46311 | T114: =IF(H114="","",IF(MAX(H114,I114)<TODAY(),"Terminé",IF(H114<=TODAY(),"En cours","À venir")))
A115: EPL-2627-004 | B115: Football | C115: Premier League | D115: 2026-2027 | E115: Saison régulière | F115: 4 | G115: Premier League – Journée 4 | H115: 46277 | I115: 46279 | K115: Europe/Paris | M115: Angleterre | N115: Hommes | O115: Officiel | P115: Oui | Q115: https://www.premierleague.com/en/news/4675097/all-380-fixtures-for-202627-premier-league-season | R115: 46311 | S115: Clôture le lundi (Leeds–Newcastle) | T115: =IF(H115="","",IF(MAX(H115,I115)<TODAY(),"Terminé",IF(H115<=TODAY(),"En cours","À venir")))
A116: EPL-2627-005 | B116: Football | C116: Premier League | D116: 2026-2027 | E116: Saison régulière | F116: 5 | G116: Premier League – Journée 5 | H116: 46283 | I116: 46285 | K116: Europe/Paris | M116: Angleterre | N116: Hommes | O116: Officiel | P116: Oui | Q116: https://www.premierleague.com/en/news/4675097/all-380-fixtures-for-202627-premier-league-season | R116: 46311 | S116: Trêve internationale ensuite (21 sept.–6 oct.) | T116: =IF(H116="","",IF(MAX(H116,I116)<TODAY(),"Terminé",IF(H116<=TODAY(),"En cours","À venir")))
A117: EPL-2627-006 | B117: Football | C117: Premier League | D117: 2026-2027 | E117: Saison régulière | F117: 6 | G117: Premier League – Journée 6 | H117: 46305 | I117: 46307 | K117: Europe/Paris | M117: Angleterre | N117: Hommes | O117: Officiel | P117: Oui | Q117: https://www.premierleague.com/en/news/4675097/all-380-fixtures-for-202627-premier-league-season | R117: 46311 | T117: =IF(H117="","",IF(MAX(H117,I117)<TODAY(),"Terminé",IF(H117<=TODAY(),"En cours","À venir")))
A118: EPL-2627-007 | B118: Football | C118: Premier League | D118: 2026-2027 | E118: Saison régulière | F118: 7 | G118: Premier League – Journée 7 | H118: 46312 | I118: 46314 | K118: Europe/Paris | M118: Angleterre | N118: Hommes | O118: Officiel | P118: Oui | Q118: https://www.premierleague.com/en/news/4675097/all-380-fixtures-for-202627-premier-league-season | R118: 46311 | T118: =IF(H118="","",IF(MAX(H118,I118)<TODAY(),"Terminé",IF(H118<=TODAY(),"En cours","À venir")))
A119: EPL-2627-008 | B119: Football | C119: Premier League | D119: 2026-2027 | E119: Saison régulière | F119: 8 | G119: Premier League – Journée 8 | H119: 46318 | I119: 46320 | K119: Europe/Paris | M119: Angleterre | N119: Hommes | O119: Provisoire | P119: Oui | Q119: https://www.premierleague.com/en/news/4675097/all-380-fixtures-for-202627-premier-league-season | R119: 46311 | S119: Ouverture ven. 23/10 ; date du dernier match non vérifiée | T119: =IF(H119="","",IF(MAX(H119,I119)<TODAY(),"Terminé",IF(H119<=TODAY(),"En cours","À venir")))
A120: EPL-2627-009 | B120: Football | C120: Premier League | D120: 2026-2027 | E120: Saison régulière | F120: 9 | G120: Premier League – Journée 9 | H120: 46326 | I120: 46328 | K120: Europe/Paris | M120: Angleterre | N120: Hommes | O120: Officiel | P120: Oui | Q120: https://www.premierleague.com/en/news/4675097/all-380-fixtures-for-202627-premier-league-season | R120: 46311 | T120: =IF(H120="","",IF(MAX(H120,I120)<TODAY(),"Terminé",IF(H120<=TODAY(),"En cours","À venir")))
A121: EPL-2627-010 | B121: Football | C121: Premier League | D121: 2026-2027 | E121: Saison régulière | F121: 10 | G121: Premier League – Journée 10 | H121: 46332 | I121: 46334 | K121: Europe/Paris | M121: Angleterre | N121: Hommes | O121: Officiel | P121: Oui | Q121: https://www.premierleague.com/en/news/4675097/all-380-fixtures-for-202627-premier-league-season | R121: 46311 | S121: Présence d'un match le lundi 9/11 non vérifiée | T121: =IF(H121="","",IF(MAX(H121,I121)<TODAY(),"Terminé",IF(H121<=TODAY(),"En cours","À venir")))
A122: EPL-2627-011 | B122: Football | C122: Premier League | D122: 2026-2027 | E122: Saison régulière | F122: 11 | G122: Premier League – Journée 11 | H122: 46347 | I122: 46349 | K122: Europe/Paris | M122: Angleterre | N122: Hommes | O122: Officiel | P122: Oui | Q122: https://www.premierleague.com/en/news/4675097/all-380-fixtures-for-202627-premier-league-season | R122: 46311 | S122: Clôture lun. 23/11 (Brentford–Everton) | T122: =IF(H122="","",IF(MAX(H122,I122)<TODAY(),"Terminé",IF(H122<=TODAY(),"En cours","À venir")))
A123: EPL-2627-012 | B123: Football | C123: Premier League | D123: 2026-2027 | E123: Saison régulière | F123: 12 | G123: Premier League – Journée 12 | H123: 46353 | I123: 46355 | K123: Europe/Paris | M123: Angleterre | N123: Hommes | O123: Officiel | P123: Oui | Q123: https://www.premierleague.com/en/news/4675097/all-380-fixtures-for-202627-premier-league-season | R123: 46311 | T123: =IF(H123="","",IF(MAX(H123,I123)<TODAY(),"Terminé",IF(H123<=TODAY(),"En cours","À venir")))
A124: EPL-2627-013 | B124: Football | C124: Premier League | D124: 2026-2027 | E124: Saison régulière | F124: 13 | G124: Premier League – Journée 13 | H124: 46358 | I124: 46358 | K124: Europe/Paris | M124: Angleterre | N124: Hommes | O124: Provisoire | P124: Oui | Q124: https://www.premierleague.com/en/news/4675097/all-380-fixtures-for-202627-premier-league-season | R124: 46311 | S124: Journée en semaine ; 9 matchs le mercredi 2/12, date du 10e non vérifiée | T124: =IF(H124="","",IF(MAX(H124,I124)<TODAY(),"Terminé",IF(H124<=TODAY(),"En cours","À venir")))
A125: EPL-2627-014 | B125: Football | C125: Premier League | D125: 2026-2027 | E125: Saison régulière | F125: 14 | G125: Premier League – Journée 14 | H125: 46360 | I125: 46363 | K125: Europe/Paris | M125: Angleterre | N125: Hommes | O125: Provisoire | P125: Oui | Q125: https://www.arsenal.com/news/arsenals-202627-premier-league-fixture-list-aONqx5R7tK9m | R125: 46311 | S125: Date nominale samedi 05/12 ; fenêtre ven.–lun. ; programmation TV non publiée | T125: =IF(H125="","",IF(MAX(H125,I125)<TODAY(),"Terminé",IF(H125<=TODAY(),"En cours","À venir")))
A126: EPL-2627-015 | B126: Football | C126: Premier League | D126: 2026-2027 | E126: Saison régulière | F126: 15 | G126: Premier League – Journée 15 | H126: 46367 | I126: 46370 | K126: Europe/Paris | M126: Angleterre | N126: Hommes | O126: Provisoire | P126: Oui | Q126: https://www.arsenal.com/news/arsenals-202627-premier-league-fixture-list-aONqx5R7tK9m | R126: 46311 | S126: Date nominale samedi 12/12 ; fenêtre ven.–lun. ; programmation TV non publiée | T126: =IF(H126="","",IF(MAX(H126,I126)<TODAY(),"Terminé",IF(H126<=TODAY(),"En cours","À venir")))
A127: EPL-2627-016 | B127: Football | C127: Premier League | D127: 2026-2027 | E127: Saison régulière | F127: 16 | G127: Premier League – Journée 16 | H127: 46374 | I127: 46377 | K127: Europe/Paris | M127: Angleterre | N127: Hommes | O127: Provisoire | P127: Oui | Q127: https://www.arsenal.com/news/arsenals-202627-premier-league-fixture-list-aONqx5R7tK9m | R127: 46311 | S127: Date nominale samedi 19/12 ; fenêtre ven.–lun. ; programmation TV non publiée | T127: =IF(H127="","",IF(MAX(H127,I127)<TODAY(),"Terminé",IF(H127<=TODAY(),"En cours","À venir")))
A128: EPL-2627-017 | B128: Football | C128: Premier League | D128: 2026-2027 | E128: Saison régulière | F128: 17 | G128: Premier League – Journée 17 | H128: 46382 | I128: 46384 | K128: Europe/Paris | M128: Angleterre | N128: Hommes | O128: Provisoire | P128: Oui | Q128: https://www.premierleague.com/en/news/4675097/all-380-fixtures-for-202627-premier-league-season | R128: 46311 | S128: Boxing Day (7 matchs le 26/12) ; certains matchs le 27/12 | T128: =IF(H128="","",IF(MAX(H128,I128)<TODAY(),"Terminé",IF(H128<=TODAY(),"En cours","À venir")))
A129: EPL-2627-018 | B129: Football | C129: Premier League | D129: 2026-2027 | E129: Saison régulière | F129: 18 | G129: Premier League – Journée 18 | H129: 46385 | I129: 46386 | K129: Europe/Paris | M129: Angleterre | N129: Hommes | O129: Provisoire | P129: Oui | Q129: https://www.premierleague.com/en/news/4675097/all-380-fixtures-for-202627-premier-league-season | R129: 46311 | S129: Journée en semaine (mar. 29 et mer. 30 déc.) | T129: =IF(H129="","",IF(MAX(H129,I129)<TODAY(),"Terminé",IF(H129<=TODAY(),"En cours","À venir")))
A130: EPL-2627-019 | B130: Football | C130: Premier League | D130: 2026-2027 | E130: Saison régulière | F130: 19 | G130: Premier League – Journée 19 | H130: 46388 | I130: 46390 | K130: Europe/Paris | M130: Angleterre | N130: Hommes | O130: Provisoire | P130: Oui | Q130: https://www.premierleague.com/en/news/4675097/all-380-fixtures-for-202627-premier-league-season | R130: 46311 | S130: Matchs du ven. 1er au dim. 3 janvier | T130: =IF(H130="","",IF(MAX(H130,I130)<TODAY(),"Terminé",IF(H130<=TODAY(),"En cours","À venir")))
A131: EPL-2627-020 | B131: Football | C131: Premier League | D131: 2026-2027 | E131: Saison régulière | F131: 20 | G131: Premier League – Journée 20 | H131: 46392 | I131: 46394 | K131: Europe/Paris | M131: Angleterre | N131: Hommes | O131: Provisoire | P131: Oui | Q131: https://www.premierleague.com/en/news/4675097/all-380-fixtures-for-202627-premier-league-season | R131: 46311 | S131: Journée en semaine (mar. 5 au jeu. 7 janvier) | T131: =IF(H131="","",IF(MAX(H131,I131)<TODAY(),"Terminé",IF(H131<=TODAY(),"En cours","À venir")))
A132: EPL-2627-021 | B132: Football | C132: Premier League | D132: 2026-2027 | E132: Saison régulière | F132: 21 | G132: Premier League – Journée 21 | H132: 46402 | I132: 46405 | K132: Europe/Paris | M132: Angleterre | N132: Hommes | O132: Provisoire | P132: Oui | Q132: https://www.arsenal.com/news/arsenals-202627-premier-league-fixture-list-aONqx5R7tK9m | R132: 46311 | S132: Date nominale samedi 16/01 ; fenêtre ven.–lun. ; programmation TV non publiée | T132: =IF(H132="","",IF(MAX(H132,I132)<TODAY(),"Terminé",IF(H132<=TODAY(),"En cours","À venir")))
A133: EPL-2627-022 | B133: Football | C133: Premier League | D133: 2026-2027 | E133: Saison régulière | F133: 22 | G133: Premier League – Journée 22 | H133: 46409 | I133: 46412 | K133: Europe/Paris | M133: Angleterre | N133: Hommes | O133: Provisoire | P133: Oui | Q133: https://www.arsenal.com/news/arsenals-202627-premier-league-fixture-list-aONqx5R7tK9m | R133: 46311 | S133: Date nominale samedi 23/01 ; fenêtre ven.–lun. ; programmation TV non publiée | T133: =IF(H133="","",IF(MAX(H133,I133)<TODAY(),"Terminé",IF(H133<=TODAY(),"En cours","À venir")))
A134: EPL-2627-023 | B134: Football | C134: Premier League | D134: 2026-2027 | E134: Saison régulière | F134: 23 | G134: Premier League – Journée 23 | H134: 46416 | I134: 46419 | K134: Europe/Paris | M134: Angleterre | N134: Hommes | O134: Provisoire | P134: Oui | Q134: https://www.arsenal.com/news/arsenals-202627-premier-league-fixture-list-aONqx5R7tK9m | R134: 46311 | S134: Date nominale samedi 30/01 ; fenêtre ven.–lun. ; programmation TV non publiée | T134: =IF(H134="","",IF(MAX(H134,I134)<TODAY(),"Terminé",IF(H134<=TODAY(),"En cours","À venir")))
A135: EPL-2627-024 | B135: Football | C135: Premier League | D135: 2026-2027 | E135: Saison régulière | F135: 24 | G135: Premier League – Journée 24 | H135: 46423 | I135: 46426 | K135: Europe/Paris | M135: Angleterre | N135: Hommes | O135: Provisoire | P135: Oui | Q135: https://www.arsenal.com/news/arsenals-202627-premier-league-fixture-list-aONqx5R7tK9m | R135: 46311 | S135: Date nominale samedi 06/02 ; fenêtre ven.–lun. ; programmation TV non publiée | T135: =IF(H135="","",IF(MAX(H135,I135)<TODAY(),"Terminé",IF(H135<=TODAY(),"En cours","À venir")))
... A148: EPL-2627-037 | B148: Football | C148: Premier League | D148: 2026-2027 | E148: Saison régulière | F148: 37 | G148: Premier League – Journée 37 | H148: 46530 | I148: 46530 | K148: Europe/Paris | M148: Angleterre | N148: Hommes | O148: Provisoire | P148: Oui | Q148: https://www.premierleague.com/en/news/4675097/all-380-fixtures-for-202627-premier-league-season | R148: 46311 | S148: Date nominale dimanche 23/05 ; programmation TV non publiée | T148: =IF(H148="","",IF(MAX(H148,I148)<TODAY(),"Terminé",IF(H148<=TODAY(),"En cours","À venir")))
A149: EPL-2627-038 | B149: Football | C149: Premier League | D149: 2026-2027 | E149: Saison régulière | F149: 38 | G149: Premier League – Journée 38 | H149: 46537 | I149: 46537 | J149: 17:00 | K149: Europe/Paris | M149: Angleterre | N149: Hommes | O149: Officiel | P149: Oui | Q149: https://www.premierleague.com/en/news/4675508/premier-league-fixture-schedulereleased-for-season-202627 | R149: 46311 | S149: Dernière journée, tous les matchs à 16h00 (heure UK) | T149: =IF(H149="","",IF(MAX(H149,I149)<TODAY(),"Terminé",IF(H149<=TODAY(),"En cours","À venir")))
A150: UCL-2627-001 | B150: Football | C150: UEFA Champions League | D150: 2026-2027 | E150: Phase de ligue | F150: 1 | G150: Ligue des champions – Journée 1 | H150: 46273 | I150: 46275 | K150: Europe/Paris | M150: Europe | N150: Hommes | O150: Officiel | P150: Oui | Q150: https://www.uefa.com/uefachampionsleague/news/02a6-20d57cfcd03e-407c22a7f465-1000--2026-27-champions-league-teams-dates-draws-format-final/ | R150: 46311 | S150: Journée sur 3 jours (mar.–jeu.) | T150: =IF(H150="","",IF(MAX(H150,I150)<TODAY(),"Terminé",IF(H150<=TODAY(),"En cours","À venir")))
A151: UCL-2627-002 | B151: Football | C151: UEFA Champions League | D151: 2026-2027 | E151: Phase de ligue | F151: 2 | G151: Ligue des champions – Journée 2 | H151: 46308 | I151: 46309 | K151: Europe/Paris | M151: Europe | N151: Hommes | O151: Officiel | P151: Oui | Q151: https://www.uefa.com/uefachampionsleague/news/02a6-20d57cfcd03e-407c22a7f465-1000--2026-27-champions-league-teams-dates-draws-format-final/ | R151: 46311 | S151: Journée disputée | T151: =IF(H151="","",IF(MAX(H151,I151)<TODAY(),"Terminé",IF(H151<=TODAY(),"En cours","À venir")))
A152: UCL-2627-003 | B152: Football | C152: UEFA Champions League | D152: 2026-2027 | E152: Phase de ligue | F152: 3 | G152: Ligue des champions – Journée 3 | H152: 46315 | I152: 46316 | K152: Europe/Paris | M152: Europe | N152: Hommes | O152: Officiel | P152: Oui | Q152: https://www.uefa.com/uefachampionsleague/news/02a6-20d57cfcd03e-407c22a7f465-1000--2026-27-champions-league-teams-dates-draws-format-final/ | R152: 46311 | T152: =IF(H152="","",IF(MAX(H152,I152)<TODAY(),"Terminé",IF(H152<=TODAY(),"En cours","À venir")))
A153: UCL-2627-004 | B153: Football | C153: UEFA Champions League | D153: 2026-2027 | E153: Phase de ligue | F153: 4 | G153: Ligue des champions – Journée 4 | H153: 46329 | I153: 46330 | K153: Europe/Paris | M153: Europe | N153: Hommes | O153: Officiel | P153: Oui | Q153: https://www.uefa.com/uefachampionsleague/news/02a6-20d57cfcd03e-407c22a7f465-1000--2026-27-champions-league-teams-dates-draws-format-final/ | R153: 46311 | T153: =IF(H153="","",IF(MAX(H153,I153)<TODAY(),"Terminé",IF(H153<=TODAY(),"En cours","À venir")))
A154: UCL-2627-005 | B154: Football | C154: UEFA Champions League | D154: 2026-2027 | E154: Phase de ligue | F154: 5 | G154: Ligue des champions – Journée 5 | H154: 46350 | I154: 46351 | K154: Europe/Paris | M154: Europe | N154: Hommes | O154: Officiel | P154: Oui | Q154: https://www.uefa.com/uefachampionsleague/news/02a6-20d57cfcd03e-407c22a7f465-1000--2026-27-champions-league-teams-dates-draws-format-final/ | R154: 46311 | T154: =IF(H154="","",IF(MAX(H154,I154)<TODAY(),"Terminé",IF(H154<=TODAY(),"En cours","À venir")))
A155: UCL-2627-006 | B155: Football | C155: UEFA Champions League | D155: 2026-2027 | E155: Phase de ligue | F155: 6 | G155: Ligue des champions – Journée 6 | H155: 46364 | I155: 46365 | K155: Europe/Paris | M155: Europe | N155: Hommes | O155: Officiel | P155: Oui | Q155: https://www.uefa.com/uefachampionsleague/news/02a6-20d57cfcd03e-407c22a7f465-1000--2026-27-champions-league-teams-dates-draws-format-final/ | R155: 46311 | T155: =IF(H155="","",IF(MAX(H155,I155)<TODAY(),"Terminé",IF(H155<=TODAY(),"En cours","À venir")))
A156: UCL-2627-007 | B156: Football | C156: UEFA Champions League | D156: 2026-2027 | E156: Phase de ligue | F156: 7 | G156: Ligue des champions – Journée 7 | H156: 46406 | I156: 46407 | K156: Europe/Paris | M156: Europe | N156: Hommes | O156: Officiel | P156: Oui | Q156: https://www.uefa.com/uefachampionsleague/news/02a6-20d57cfcd03e-407c22a7f465-1000--2026-27-champions-league-teams-dates-draws-format-final/ | R156: 46311 | T156: =IF(H156="","",IF(MAX(H156,I156)<TODAY(),"Terminé",IF(H156<=TODAY(),"En cours","À venir")))
A157: UCL-2627-008 | B157: Football | C157: UEFA Champions League | D157: 2026-2027 | E157: Phase de ligue | F157: 8 | G157: Ligue des champions – Journée 8 | H157: 46414 | I157: 46414 | K157: Europe/Paris | M157: Europe | N157: Hommes | O157: Officiel | P157: Oui | Q157: https://www.uefa.com/uefachampionsleague/news/02a6-20d57cfcd03e-407c22a7f465-1000--2026-27-champions-league-teams-dates-draws-format-final/ | R157: 46311 | S157: 18 matchs simultanés | T157: =IF(H157="","",IF(MAX(H157,I157)<TODAY(),"Terminé",IF(H157<=TODAY(),"En cours","À venir")))
A158: UCL-2627-009 | B158: Football | C158: UEFA Champions League | D158: 2026-2027 | E158: Barrages | F158: Aller | G158: Ligue des champions – Barrages (aller) | H158: 46434 | I158: 46435 | K158: Europe/Paris | M158: Europe | N158: Hommes | O158: Officiel | P158: Oui | Q158: https://www.uefa.com/uefachampionsleague/news/02a8-21717d0c6cb5-03a9a5ff1552-1000--champions-league-league-phase-draw-pots-confirmed/ | R158: 46311 | T158: =IF(H158="","",IF(MAX(H158,I158)<TODAY(),"Terminé",IF(H158<=TODAY(),"En cours","À venir")))
...

Sheet Référentiels
A1: code | B1: sport | C1: competition | D1: granularite | E1: source_officielle | F1: nb_epreuves | G1: prochaine_epreuve | H1: sports | J1: statuts | K1: genres | L1: oui_non
A2: L1 | B2: Football | C2: Ligue 1 | D2: 1 ligne par journée | E2: https://ligue1.com | F2: =COUNTIF('Épreuves'!$C$2:$C$5000,C2) | G2: =IFERROR(1/(1/_xlfn.MINIFS('Épreuves'!$H$2:$H$5000,'Épreuves'!$C$2:$C$5000,C2,'Épreuves'!$H$2:$H$5000,">="&TODAY())),"") | H2: Basketball | J2: Officiel | K2: Hommes | L2: Oui
A3: L2 | B3: Football | C3: Ligue 2 | D3: 1 ligne par journée | E3: https://www.ligue2.fr | F3: =COUNTIF('Épreuves'!$C$2:$C$5000,C3) | G3: =IFERROR(1/(1/_xlfn.MINIFS('Épreuves'!$H$2:$H$5000,'Épreuves'!$C$2:$C$5000,C3,'Épreuves'!$H$2:$H$5000,">="&TODAY())),"") | H3: Biathlon | J3: Provisoire | K3: Femmes | L3: Non
A4: LIGA | B4: Football | C4: LaLiga | D4: 1 ligne par journée | E4: https://www.laliga.com | F4: =COUNTIF('Épreuves'!$C$2:$C$5000,C4) | G4: =IFERROR(1/(1/_xlfn.MINIFS('Épreuves'!$H$2:$H$5000,'Épreuves'!$C$2:$C$5000,C4,'Épreuves'!$H$2:$H$5000,">="&TODAY())),"") | H4: Cyclisme sur route | J4: À confirmer | K4: Mixte
A5: EPL | B5: Football | C5: Premier League | D5: 1 ligne par journée | E5: https://www.premierleague.com | F5: =COUNTIF('Épreuves'!$C$2:$C$5000,C5) | G5: =IFERROR(1/(1/_xlfn.MINIFS('Épreuves'!$H$2:$H$5000,'Épreuves'!$C$2:$C$5000,C5,'Épreuves'!$H$2:$H$5000,">="&TODAY())),"") | H5: Football | J5: Reporté
A6: UCL | B6: Football | C6: UEFA Champions League | D6: 1 ligne par journée ou par match aller/retour | E6: https://www.uefa.com/uefachampionsleague | F6: =COUNTIF('Épreuves'!$C$2:$C$5000,C6) | G6: =IFERROR(1/(1/_xlfn.MINIFS('Épreuves'!$H$2:$H$5000,'Épreuves'!$C$2:$C$5000,C6,'Épreuves'!$H$2:$H$5000,">="&TODAY())),"") | H6: Football américain | J6: Annulé
A7: UNL | B7: Football | C7: UEFA Nations League | D7: 1 ligne par journée ou par tour | E7: https://www.uefa.com/uefanationsleague | F7: =COUNTIF('Épreuves'!$C$2:$C$5000,C7) | G7: =IFERROR(1/(1/_xlfn.MINIFS('Épreuves'!$H$2:$H$5000,'Épreuves'!$C$2:$C$5000,C7,'Épreuves'!$H$2:$H$5000,">="&TODAY())),"") | H7: Golf
A8: T14 | B8: Rugby | C8: Top 14 | D8: 1 ligne par journée | E8: https://top14.lnr.fr | F8: =COUNTIF('Épreuves'!$C$2:$C$5000,C8) | G8: =IFERROR(1/(1/_xlfn.MINIFS('Épreuves'!$H$2:$H$5000,'Épreuves'!$C$2:$C$5000,C8,'Épreuves'!$H$2:$H$5000,">="&TODAY())),"") | H8: Handball
A9: PD2 | B9: Rugby | C9: Pro D2 | D9: 1 ligne par journée | E9: https://prod2.lnr.fr | F9: =COUNTIF('Épreuves'!$C$2:$C$5000,C9) | G9: =IFERROR(1/(1/_xlfn.MINIFS('Épreuves'!$H$2:$H$5000,'Épreuves'!$C$2:$C$5000,C9,'Épreuves'!$H$2:$H$5000,">="&TODAY())),"") | H9: Hockey sur glace
A10: CC | B10: Rugby | C10: Champions Cup | D10: 1 ligne par journée ou par tour | E10: https://www.epcrugby.com | F10: =COUNTIF('Épreuves'!$C$2:$C$5000,C10) | G10: =IFERROR(1/(1/_xlfn.MINIFS('Épreuves'!$H$2:$H$5000,'Épreuves'!$C$2:$C$5000,C10,'Épreuves'!$H$2:$H$5000,">="&TODAY())),"") | H10: Moto
A11: SL | B11: Handball | C11: StarLigue | D11: 1 ligne par journée | E11: https://www.lnh.fr | F11: =COUNTIF('Épreuves'!$C$2:$C$5000,C11) | G11: =IFERROR(1/(1/_xlfn.MINIFS('Épreuves'!$H$2:$H$5000,'Épreuves'!$C$2:$C$5000,C11,'Épreuves'!$H$2:$H$5000,">="&TODAY())),"") | H11: Rallye
A12: MAG | B12: Hockey sur glace | C12: Ligue Magnus | D12: 1 ligne par journée ou par tour de play-offs | E12: https://www.hockeyfrance.com | F12: =COUNTIF('Épreuves'!$C$2:$C$5000,C12) | G12: =IFERROR(1/(1/_xlfn.MINIFS('Épreuves'!$H$2:$H$5000,'Épreuves'!$C$2:$C$5000,C12,'Épreuves'!$H$2:$H$5000,">="&TODAY())),"") | H12: Rugby
A13: SPK | B13: Volley-ball | C13: Marmara SpikeLigue | D13: 1 ligne par journée ou par tour de play-offs | E13: https://www.lnv.fr | F13: =COUNTIF('Épreuves'!$C$2:$C$5000,C13) | G13: =IFERROR(1/(1/_xlfn.MINIFS('Épreuves'!$H$2:$H$5000,'Épreuves'!$C$2:$C$5000,C13,'Épreuves'!$H$2:$H$5000,">="&TODAY())),"") | H13: Ski alpin
A14: NBA | B14: Basketball | C14: NBA | D14: 1 ligne par semaine + temps forts | E14: https://www.nba.com | F14: =COUNTIF('Épreuves'!$C$2:$C$5000,C14) | G14: =IFERROR(1/(1/_xlfn.MINIFS('Épreuves'!$H$2:$H$5000,'Épreuves'!$C$2:$C$5000,C14,'Épreuves'!$H$2:$H$5000,">="&TODAY())),"") | H14: Sport automobile
A15: NFL | B15: Football américain | C15: NFL | D15: 1 ligne par semaine (Week) | E15: https://www.nfl.com | F15: =COUNTIF('Épreuves'!$C$2:$C$5000,C15) | G15: =IFERROR(1/(1/_xlfn.MINIFS('Épreuves'!$H$2:$H$5000,'Épreuves'!$C$2:$C$5000,C15,'Épreuves'!$H$2:$H$5000,">="&TODAY())),"") | H15: Tennis
A16: PGA | B16: Golf | C16: PGA Tour | D16: 1 ligne par tournoi | E16: https://www.pgatour.com | F16: =COUNTIF('Épreuves'!$C$2:$C$5000,C16) | G16: =IFERROR(1/(1/_xlfn.MINIFS('Épreuves'!$H$2:$H$5000,'Épreuves'!$C$2:$C$5000,C16,'Épreuves'!$H$2:$H$5000,">="&TODAY())),"") | H16: Volley-ball
A17: F1 | B17: Sport automobile | C17: Formule 1 | D17: 1 ligne par week-end de Grand Prix | E17: https://www.formula1.com | F17: =COUNTIF('Épreuves'!$C$2:$C$5000,C17) | G17: =IFERROR(1/(1/_xlfn.MINIFS('Épreuves'!$H$2:$H$5000,'Épreuves'!$C$2:$C$5000,C17,'Épreuves'!$H$2:$H$5000,">="&TODAY())),"")
A18: MGP | B18: Moto | C18: MotoGP | D18: 1 ligne par week-end de Grand Prix | E18: https://www.motogp.com | F18: =COUNTIF('Épreuves'!$C$2:$C$5000,C18) | G18: =IFERROR(1/(1/_xlfn.MINIFS('Épreuves'!$H$2:$H$5000,'Épreuves'!$C$2:$C$5000,C18,'Épreuves'!$H$2:$H$5000,">="&TODAY())),"")
A19: WRC | B19: Rallye | C19: WRC | D19: 1 ligne par rallye | E19: https://www.wrc.com | F19: =COUNTIF('Épreuves'!$C$2:$C$5000,C19) | G19: =IFERROR(1/(1/_xlfn.MINIFS('Épreuves'!$H$2:$H$5000,'Épreuves'!$C$2:$C$5000,C19,'Épreuves'!$H$2:$H$5000,">="&TODAY())),"")
A20: GC | B20: Tennis | C20: Grand Chelem | D20: 1 ligne par tournoi | E20: https://www.itftennis.com | F20: =COUNTIF('Épreuves'!$C$2:$C$5000,C20) | G20: =IFERROR(1/(1/_xlfn.MINIFS('Épreuves'!$H$2:$H$5000,'Épreuves'!$C$2:$C$5000,C20,'Épreuves'!$H$2:$H$5000,">="&TODAY())),"")
A21: UCI | B21: Cyclisme sur route | C21: UCI WorldTour | D21: 1 ligne par course | E21: https://www.uci.org | F21: =COUNTIF('Épreuves'!$C$2:$C$5000,C21) | G21: =IFERROR(1/(1/_xlfn.MINIFS('Épreuves'!$H$2:$H$5000,'Épreuves'!$C$2:$C$5000,C21,'Épreuves'!$H$2:$H$5000,">="&TODAY())),"")
A22: UCIM | B22: Cyclisme sur route | C22: Championnats du monde UCI | D22: 1 ligne par épreuve | E22: https://www.uci.org | F22: =COUNTIF('Épreuves'!$C$2:$C$5000,C22) | G22: =IFERROR(1/(1/_xlfn.MINIFS('Épreuves'!$H$2:$H$5000,'Épreuves'!$C$2:$C$5000,C22,'Épreuves'!$H$2:$H$5000,">="&TODAY())),"")
A23: SKI | B23: Ski alpin | C23: Coupe du monde de ski alpin | D23: 1 ligne par épreuve | E23: https://www.fis-ski.com | F23: =COUNTIF('Épreuves'!$C$2:$C$5000,C23) | G23: =IFERROR(1/(1/_xlfn.MINIFS('Épreuves'!$H$2:$H$5000,'Épreuves'!$C$2:$C$5000,C23,'Épreuves'!$H$2:$H$5000,">="&TODAY())),"")
A24: SKIM | B24: Ski alpin | C24: Championnats du monde de ski alpin | D24: 1 ligne par épreuve | E24: https://www.fis-ski.com | F24: =COUNTIF('Épreuves'!$C$2:$C$5000,C24) | G24: =IFERROR(1/(1/_xlfn.MINIFS('Épreuves'!$H$2:$H$5000,'Épreuves'!$C$2:$C$5000,C24,'Épreuves'!$H$2:$H$5000,">="&TODAY())),"")
A25: BIA | B25: Biathlon | C25: Coupe du monde de biathlon | D25: 1 ligne par épreuve | E25: https://www.biathlonworld.com | F25: =COUNTIF('Épreuves'!$C$2:$C$5000,C25) | G25: =IFERROR(1/(1/_xlfn.MINIFS('Épreuves'!$H$2:$H$5000,'Épreuves'!$C$2:$C$5000,C25,'Épreuves'!$H$2:$H$5000,">="&TODAY())),"")
A26: BIAM | B26: Biathlon | C26: Championnats du monde de biathlon | D26: 1 ligne par épreuve | E26: https://www.biathlonworld.com | F26: =COUNTIF('Épreuves'!$C$2:$C$5000,C26) | G26: =IFERROR(1/(1/_xlfn.MINIFS('Épreuves'!$H$2:$H$5000,'Épreuves'!$C$2:$C$5000,C26,'Épreuves'!$H$2:$H$5000,">="&TODAY())),"")
C27: Total | F27: =SUM(F2:F26)
